{"trial_id": "a7f22891e40cda6024f23506cda9577c", "hyperparameters": {"space": [{"class_name": "Choice", "config": {"name": "activation", "default": "relu", "conditions": [], "values": ["relu", "tanh", "sigmoid"], "ordered": false}}, {"class_name": "Int", "config": {"name": "first_units", "default": null, "conditions": [], "min_value": 1, "max_value": 80, "step": 5, "sampling": null}}, {"class_name": "Int", "config": {"name": "num_layers", "default": null, "conditions": [], "min_value": 1, "max_value": 5, "step": 1, "sampling": null}}, {"class_name": "Int", "config": {"name": "units_0", "default": null, "conditions": [], "min_value": 1, "max_value": 60, "step": 5, "sampling": null}}, {"class_name": "Int", "config": {"name": "units_1", "default": null, "conditions": [], "min_value": 1, "max_value": 60, "step": 5, "sampling": null}}, {"class_name": "Int", "config": {"name": "units_2", "default": null, "conditions": [], "min_value": 1, "max_value": 60, "step": 5, "sampling": null}}, {"class_name": "Int", "config": {"name": "units_3", "default": null, "conditions": [], "min_value": 1, "max_value": 60, "step": 5, "sampling": null}}], "values": {"activation": "sigmoid", "first_units": 71, "num_layers": 2, "units_0": 46, "units_1": 11, "units_2": 51, "units_3": 21, "tuner/epochs": 3, "tuner/initial_epoch": 0, "tuner/bracket": 2, "tuner/round": 0}}, "metrics": {"metrics": {"loss": {"direction": "min", "observations": [{"value": [0.5965541005134583], "step": 0}]}, "accuracy": {"direction": "max", "observations": [{"value": [0.7274918556213379], "step": 0}]}, "val_loss": {"direction": "min", "observations": [{"value": [0.5765259265899658], "step": 0}]}, "val_accuracy": {"direction": "max", "observations": [{"value": [0.7217492461204529], "step": 0}]}}}, "score": 0.7217492461204529, "best_step": 0, "status": "COMPLETED"}